varipeps/config.py
varipeps/__init__.py
varipeps/__version__.py
varipeps/global_state.py
varipeps/typing.py
varipeps/mapping/maple_leaf.py
varipeps/mapping/honeycomb.py
varipeps/mapping/__init__.py
varipeps/mapping/triangular.py
varipeps/mapping/model.py
varipeps/mapping/florett_pentagon.py
varipeps/mapping/kagome.py
varipeps/mapping/square_kagome.py
varipeps/contractions/definitions.py
varipeps/contractions/__init__.py
varipeps/contractions/apply.py
varipeps/expectation/triangular_helpers.py
varipeps/expectation/two_sites.py
varipeps/expectation/one_site.py
varipeps/expectation/triangular_next_nearest.py
varipeps/expectation/__init__.py
varipeps/expectation/spiral_helpers.py
varipeps/expectation/triangular_two_sites.py
varipeps/expectation/three_sites.py
varipeps/expectation/model.py
varipeps/expectation/triangular_one_site.py
varipeps/expectation/four_sites.py
varipeps/expectation/helpers.py
varipeps/expectation/structure_factor.py
varipeps/peps/unitcell.py
varipeps/peps/__init__.py
varipeps/peps/tensor.py
varipeps/corrlength/triangular_corrlength.py
varipeps/corrlength/corrlength.py
varipeps/corrlength/__init__.py
varipeps/optimization/inner_function.py
varipeps/optimization/line_search.py
varipeps/optimization/__init__.py
varipeps/optimization/optimizer.py
varipeps/optimization/basinhopping.py
varipeps/utils/slurm.py
varipeps/utils/__init__.py
varipeps/utils/random.py
varipeps/utils/svd.py
varipeps/utils/projector_dict.py
varipeps/utils/periodic_indices.py
varipeps/utils/debug_print.py
varipeps/utils/func_cache.py
varipeps/utils/extensions/svd_ffi.h
varipeps/utils/extensions/_svd_only_u_vt.cpython-311-darwin.so
varipeps/utils/extensions/svd_ffi.cpp
varipeps/ctmrg/absorption.py
varipeps/ctmrg/structure_factor_absorption.py
varipeps/ctmrg/triangular_projectors.py
varipeps/ctmrg/triangular_absorption.py
varipeps/ctmrg/__init__.py
varipeps/ctmrg/routine.py
varipeps/ctmrg/projectors.py
varipeps-1.4.1.dist-info/RECORD
varipeps-1.4.1.dist-info/WHEEL
varipeps-1.4.1.dist-info/METADATA
varipeps-1.4.1.dist-info/licenses/LICENSE
