Metadata-Version: 2.4
Name: variPEPS
Version: 1.4.1
Summary: Versatile tensor network library for variational ground state simulations in two spatial dimensions
Project-URL: Documentation, https://varipeps.readthedocs.io/en/stable/
Project-URL: Repository, https://github.com/variPEPS/variPEPS_Python
Project-URL: Issues, https://github.com/variPEPS/variPEPS_Python/issues
Author: Frederik Wilde, Finn Krein
Author-email: Jan Naumann <j.naumann@fu-berlin.de>, Philipp Schmoll <philipp.schmoll@fu-berlin.de>, Roberto Losada <roberto.losada@fu-berlin.de>
License-Expression: GPL-3.0-or-later
License-File: LICENSE
Keywords: automatic-differentiation,peps,physics,quantum-many-body,quantum-many-body-physics,tensor-networks,variational-optimization
Classifier: Intended Audience :: Science/Research
Classifier: Programming Language :: Python :: 3
Classifier: Topic :: Scientific/Engineering :: Physics
Requires-Python: >=3.11
Requires-Dist: h5py>=3.6.0
Requires-Dist: jax[cpu]>=0.8.1
Requires-Dist: numpy>=1.21.2
Requires-Dist: scipy>=1.7.1
Requires-Dist: tqdm-loggable>=0.1.3
Requires-Dist: tqdm[notebook]>=4.64.1
